dysonz/__init__.py
dysonz/claw_hook.py
dysonz/conveyor.py
dysonz/datas.py
dysonz/workbench.py
dysonz-0.1.1.dist-info/METADATA
dysonz-0.1.1.dist-info/WHEEL
dysonz-0.1.1.dist-info/top_level.txt
dysonz-0.1.1.dist-info/RECORD
